bgprecorder/__init__.py
bgprecorder/bgprecorder.py
bgprecorder/cli.py
bgprecorder/util.py
bgprecorder-0.1.4.dist-info/entry_points.txt
bgprecorder-0.1.4.dist-info/WHEEL
bgprecorder-0.1.4.dist-info/METADATA
bgprecorder-0.1.4.dist-info/RECORD
